{
	"modules":
	{
		"child_panel":				{"url":"/modules/panel/child.html","name_for_search":""},

		"home":						{"url":"/modules/home.html","name_for_search":"Home page (nightstudy)"},
		"participant":				{"url":"/modules/participant/participant.html","table_id":"20010469","name_for_search":"Participant (nightstudy)"},
		"participant_login_setup":	{"url":"/modules/participant/participant_login_setup.html","table_id":"20010471","name_for_search":""},
		"clinical_trials_notes":	{"url":"/modules/participant/task-notes.html","table_id":"20010470","name_for_search":"Task notes (nightstudy)"},
		"site_filter":				{"table_id":"20010473","name_for_search":""}
	}
}
